[{"Id":3,"Name":"Patrice Roy","Email":"Patrice.Roy@clg.qc.ca","Password":"Password_123","Created":1601500919},{"Id":4,"Name":"Saliha Yacoub","Email":"Saliha.Yacoub@clg.qc.ca","Password":"Password_123","Created":1601501044},{"Id":5,"Name":"Kyle Ross","Email":"Kyle.Ross@clg.qc.ca","Password":"Password_123","Created":1601564566},{"Id":6,"Name":"Rachid Kadouche","Email":"Rachid.Kadouche@clg.qc.ca","Password":"Password_123","Created":1603112394},{"Id":7,"Name":"Warda Moussadak","Email":"Warda.Moussadak@clg.qc.ca","Password":"123","Created":1603740612},{"Id":9,"Name":"François Boileau","Email":"Francois.Boileau@clg.qc.ca","Password":"123","Created":1636032311},{"Id":10,"Name":"Alex Brosseau","Email":"brosseau.alex@outlook.com","Password":"123","AvatarGUID":"aadf40b0-5f46-11ec-ac74-fffa6c46d250","Created":1639751766},{"Id":11,"Name":"AlexTry","Email":"brosseau.alex.1@outlook.com","Password":"123","AvatarGUID":"aa6a6c20-6e6b-11ec-8d24-719487d3d8d5","Created":1641416924}]